{
   "name":  "Query", 
   "result": 2.967323,
   "timing": 2.967323,
   "cardinality": 0,
   "extra-info": "-- PRAGMA profiling_mode = 'detailed';\n;\nSELECT min(mi_idx.info) AS rating,\n       min(t.title) AS western_dark_production\nFROM info_type AS it1,\n     info_type AS it2,\n     keyword AS k,\n     kind_type AS kt,\n     movie_info AS mi,\n     movie_info_idx AS mi_idx,\n     movie_keyword AS mk,\n     title AS t\nWHERE it1.info = 'countries'\n  AND it2.info = 'rating'\n  AND k.keyword in ('murder',\n                    'murder-in-title')\n  AND kt.kind = 'movie'\n  AND mi.info IN ('Sweden',\n                  'Norway',\n                  'Germany',\n                  'Denmark',\n                  'Swedish',\n                  'Denish',\n                  'Norwegian',\n                  'German',\n                  'USA',\n                  'American')\n  AND mi_idx.info > '6.0'\n  AND t.production_year > 2010\n  AND (t.title like '%murder%'\n       OR t.title like '%Murder%'\n       OR t.title like '%Mord%')\n  AND kt.id = t.kind_id\n  AND t.id = mi.movie_id\n  AND t.id = mk.movie_id\n  AND t.id = mi_idx.movie_id\n  AND mk.movie_id = mi.movie_id\n  AND mk.movie_id = mi_idx.movie_id\n  AND mi.movie_id = mi_idx.movie_id\n  AND k.id = mk.keyword_id\n  AND it1.id = mi.info_type_id\n  AND it2.id = mi_idx.info_type_id;;\n\nPRAGMA profile_output='./query-log/imdb/job/hausberg-1-threads/duckdb-20250306-14-05-54/hot/14b.json';\nSELECT min(mi_idx.info) AS rating,\n       min(t.title) AS western_dark_production\nFROM info_type AS it1,\n     info_type AS it2,\n     keyword AS k,\n     kind_type AS kt,\n     movie_info AS mi,\n     movie_info_idx AS mi_idx,\n     movie_keyword AS mk,\n     title AS t\nWHERE it1.info = 'countries'\n  AND it2.info = 'rating'\n  AND k.keyword in ('murder',\n                    'murder-in-title')\n  AND kt.kind = 'movie'\n  AND mi.info IN ('Sweden',\n                  'Norway',\n                  'Germany',\n                  'Denmark',\n                  'Swedish',\n                  'Denish',\n                  'Norwegian',\n                  'German',\n                  'USA',\n                  'American')\n  AND mi_idx.info > '6.0'\n  AND t.production_year > 2010\n  AND (t.title like '%murder%'\n       OR t.title like '%Murder%'\n       OR t.title like '%Mord%')\n  AND kt.id = t.kind_id\n  AND t.id = mi.movie_id\n  AND t.id = mk.movie_id\n  AND t.id = mi_idx.movie_id\n  AND mk.movie_id = mi.movie_id\n  AND mk.movie_id = mi_idx.movie_id\n  AND mi.movie_id = mi_idx.movie_id\n  AND k.id = mk.keyword_id\n  AND it1.id = mi.info_type_id\n  AND it2.id = mi_idx.info_type_id;;\n", 
   "timings": [

   ],
   "children": [
    {
      "name": "RESULT_COLLECTOR",
      "timing":0.000022,
      "cardinality":0,
      "extra_info": "",
      "timings": [
      ],
      "children": [
       {
         "name": "UNGROUPED_AGGREGATE",
         "timing":0.000398,
         "cardinality":1,
         "extra_info": "min(#0)\nmin(#1)",
         "timings": [
         ],
         "children": [
          {
            "name": "PROJECTION",
            "timing":0.000000,
            "cardinality":1,
            "extra_info": "info\ntitle\n",
            "timings": [
            ],
            "children": [
             {
               "name": "HASH_JOIN",
               "timing":0.000057,
               "cardinality":1,
               "extra_info": "INNER\nid = keyword_id\n\n[INFOSEPARATOR]\nEC: 0\n",
               "timings": [
               ],
               "children": [
                {
                  "name": "FILTER",
                  "timing":0.001164,
                  "cardinality":1,
                  "extra_info": "((keyword = 'murder') OR (keyword = 'murder-in-title'))\n[INFOSEPARATOR]\nEC: 26834",
                  "timings": [
                  ],
                  "children": [
                   {
                     "name": "SEQ_SCAN ",
                     "timing":0.012176,
                     "cardinality":134170,
                     "extra_info": "keyword\n[INFOSEPARATOR]\nkeyword\nid\n[INFOSEPARATOR]\nEC: 26834",
                     "timings": [
                     ],
                     "children": [
                     ]
                   }
                  ]
                }
,
                {
                  "name": "HASH_JOIN",
                  "timing":0.026417,
                  "cardinality":4,
                  "extra_info": "INNER\nmovie_id = id\nmovie_id = movie_id\nmovie_id = movie_id\n\n[INFOSEPARATOR]\nEC: 0\n",
                  "timings": [
                  ],
                  "children": [
                   {
                     "name": "SEQ_SCAN ",
                     "timing":0.061264,
                     "cardinality":4523924,
                     "extra_info": "movie_keyword\n[INFOSEPARATOR]\nmovie_id\nkeyword_id\n[INFOSEPARATOR]\nFilters: movie_id<=2525793 AND movie_id IS NOT NULL\n\n[INFOSEPARATOR]\nEC: 4523930",
                     "timings": [
                     ],
                     "children": [
                     ]
                   }
,
                   {
                     "name": "HASH_JOIN",
                     "timing":0.000047,
                     "cardinality":2,
                     "extra_info": "INNER\ninfo_type_id = id\n\n[INFOSEPARATOR]\nEC: 0\n",
                     "timings": [
                     ],
                     "children": [
                      {
                        "name": "HASH_JOIN",
                        "timing":0.005117,
                        "cardinality":2,
                        "extra_info": "INNER\nmovie_id = id\nmovie_id = movie_id\n\n[INFOSEPARATOR]\nEC: 16\n",
                        "timings": [
                        ],
                        "children": [
                         {
                           "name": "PROJECTION",
                           "timing":0.000144,
                           "cardinality":706660,
                           "extra_info": "#0\n#1\n",
                           "timings": [
                           ],
                           "children": [
                            {
                              "name": "FILTER",
                              "timing":0.002741,
                              "cardinality":706660,
                              "extra_info": "(movie_id BETWEEN 2 AND 2525793)\n[INFOSEPARATOR]\nEC: 2967144",
                              "timings": [
                              ],
                              "children": [
                               {
                                 "name": "PROJECTION",
                                 "timing":0.000205,
                                 "cardinality":706674,
                                 "extra_info": "#1\n#2\n#3\n",
                                 "timings": [
                                 ],
                                 "children": [
                                  {
                                    "name": "FILTER",
                                    "timing":0.020432,
                                    "cardinality":706674,
                                    "extra_info": "IN (...)\n[INFOSEPARATOR]\nEC: 2967144",
                                    "timings": [
                                    ],
                                    "children": [
                                     {
                                       "name": "HASH_JOIN",
                                       "timing":0.405412,
                                       "cardinality":14835720,
                                       "extra_info": "MARK\ninfo = #0\n\n[INFOSEPARATOR]\nEC: 14835720\n",
                                       "timings": [
                                       ],
                                       "children": [
                                        {
                                          "name": "SEQ_SCAN ",
                                          "timing":2.027524,
                                          "cardinality":14835720,
                                          "extra_info": "movie_info\n[INFOSEPARATOR]\ninfo\nmovie_id\ninfo_type_id\n[INFOSEPARATOR]\nEC: 14835720",
                                          "timings": [
                                          ],
                                          "children": [
                                          ]
                                        }
,
                                        {
                                          "name": "COLUMN_DATA_SCAN",
                                          "timing":0.000004,
                                          "cardinality":10,
                                          "extra_info": "",
                                          "timings": [
                                          ],
                                          "children": [
                                          ]
                                        }
                                       ]
                                     }
                                    ]
                                  }
                                 ]
                               }
                              ]
                            }
                           ]
                         }
,
                         {
                           "name": "HASH_JOIN",
                           "timing":0.000033,
                           "cardinality":4,
                           "extra_info": "INNER\nkind_id = id\n\n[INFOSEPARATOR]\nEC: 14\n",
                           "timings": [
                           ],
                           "children": [
                            {
                              "name": "HASH_JOIN",
                              "timing":0.010896,
                              "cardinality":49,
                              "extra_info": "INNER\nid = movie_id\n\n[INFOSEPARATOR]\nEC: 99\n",
                              "timings": [
                              ],
                              "children": [
                               {
                                 "name": "FILTER",
                                 "timing":0.034061,
                                 "cardinality":455,
                                 "extra_info": "((id BETWEEN 2 AND 2525793) AND (contains(title, 'murder') OR contains(title, 'Murder') OR contains(title, 'Mord')))\n[INFOSEPARATOR]\nEC: 101132",
                                 "timings": [
                                 ],
                                 "children": [
                                  {
                                    "name": "SEQ_SCAN ",
                                    "timing":0.277352,
                                    "cardinality":391666,
                                    "extra_info": "title\n[INFOSEPARATOR]\ntitle\nkind_id\nid\n[INFOSEPARATOR]\nFilters: production_year>2010 AND production_year IS NOT NULL\n\n[INFOSEPARATOR]\nEC: 101132",
                                    "timings": [
                                    ],
                                    "children": [
                                    ]
                                  }
                                 ]
                               }
,
                               {
                                 "name": "HASH_JOIN",
                                 "timing":0.002810,
                                 "cardinality":259848,
                                 "extra_info": "INNER\ninfo_type_id = id\n\n[INFOSEPARATOR]\nEC: 2464\n",
                                 "timings": [
                                 ],
                                 "children": [
                                  {
                                    "name": "SEQ_SCAN ",
                                    "timing":0.054877,
                                    "cardinality":373409,
                                    "extra_info": "movie_info_idx\n[INFOSEPARATOR]\ninfo\nmovie_id\ninfo_type_id\n[INFOSEPARATOR]\nFilters: info>6.0 AND info IS NOT NULL\n\n[INFOSEPARATOR]\nEC: 276007",
                                    "timings": [
                                    ],
                                    "children": [
                                    ]
                                  }
,
                                  {
                                    "name": "FILTER",
                                    "timing":0.000005,
                                    "cardinality":1,
                                    "extra_info": "(id >= 99)\n[INFOSEPARATOR]\nEC: 1",
                                    "timings": [
                                    ],
                                    "children": [
                                     {
                                       "name": "SEQ_SCAN ",
                                       "timing":0.000011,
                                       "cardinality":1,
                                       "extra_info": "info_type\n[INFOSEPARATOR]\nid\n[INFOSEPARATOR]\nFilters: info=rating AND info IS NOT NULL\n\n[INFOSEPARATOR]\nEC: 1",
                                       "timings": [
                                       ],
                                       "children": [
                                       ]
                                     }
                                    ]
                                  }
                                 ]
                               }
                              ]
                            }
,
                            {
                              "name": "SEQ_SCAN ",
                              "timing":0.000007,
                              "cardinality":1,
                              "extra_info": "kind_type\n[INFOSEPARATOR]\nid\n[INFOSEPARATOR]\nFilters: kind=movie AND kind IS NOT NULL\n\n[INFOSEPARATOR]\nEC: 1",
                              "timings": [
                              ],
                              "children": [
                              ]
                            }
                           ]
                         }
                        ]
                      }
,
                      {
                        "name": "FILTER",
                        "timing":0.000409,
                        "cardinality":1,
                        "extra_info": "(id <= 110)\n[INFOSEPARATOR]\nEC: 1",
                        "timings": [
                        ],
                        "children": [
                         {
                           "name": "SEQ_SCAN ",
                           "timing":0.001511,
                           "cardinality":1,
                           "extra_info": "info_type\n[INFOSEPARATOR]\nid\n[INFOSEPARATOR]\nFilters: info=countries AND info IS NOT NULL\n\n[INFOSEPARATOR]\nEC: 1",
                           "timings": [
                           ],
                           "children": [
                           ]
                         }
                        ]
                      }
                     ]
                   }
                  ]
                }
               ]
             }
            ]
          }
         ]
       }
      ]
    }
   ]
}