{
   "name":  "Query", 
   "result": 0.661592,
   "timing": 0.661592,
   "cardinality": 0,
   "extra-info": "-- PRAGMA profiling_mode = 'detailed';\n;\nSELECT min(t.title) AS typical_european_movie\nFROM company_type AS ct,\n     info_type AS it,\n     movie_companies AS mc,\n     movie_info AS mi,\n     title AS t\nWHERE ct.kind = 'production companies'\n  AND mc.note like '%(theatrical)%'\n  AND mc.note like '%(France)%'\n  AND mi.info IN ('Sweden',\n                  'Norway',\n                  'Germany',\n                  'Denmark',\n                  'Swedish',\n                  'Denish',\n                  'Norwegian',\n                  'German')\n  AND t.production_year > 2005\n  AND t.id = mi.movie_id\n  AND t.id = mc.movie_id\n  AND mc.movie_id = mi.movie_id\n  AND ct.id = mc.company_type_id\n  AND it.id = mi.info_type_id;;\n\nPRAGMA profile_output='./query-log/imdb/job/hausberg-1-threads/rpt++-20250306-12-08-53/hot/5a.json';\nSELECT min(t.title) AS typical_european_movie\nFROM company_type AS ct,\n     info_type AS it,\n     movie_companies AS mc,\n     movie_info AS mi,\n     title AS t\nWHERE ct.kind = 'production companies'\n  AND mc.note like '%(theatrical)%'\n  AND mc.note like '%(France)%'\n  AND mi.info IN ('Sweden',\n                  'Norway',\n                  'Germany',\n                  'Denmark',\n                  'Swedish',\n                  'Denish',\n                  'Norwegian',\n                  'German')\n  AND t.production_year > 2005\n  AND t.id = mi.movie_id\n  AND t.id = mc.movie_id\n  AND mc.movie_id = mi.movie_id\n  AND ct.id = mc.company_type_id\n  AND it.id = mi.info_type_id;;\n", 
   "timings": [

   ],
   "children": [
    {
      "name": "RESULT_COLLECTOR",
      "timing":0.000011,
      "cardinality":0,
      "extra_info": "",
      "timings": [
      ],
      "children": [
       {
         "name": "UNGROUPED_AGGREGATE",
         "timing":0.000003,
         "cardinality":1,
         "extra_info": "min(#0)",
         "timings": [
         ],
         "children": [
          {
            "name": "PROJECTION",
            "timing":0.000000,
            "cardinality":0,
            "extra_info": "title\n",
            "timings": [
            ],
            "children": [
             {
               "name": "HASH_JOIN",
               "timing":0.000249,
               "cardinality":0,
               "extra_info": "INNER\ninfo_type_id = id\n\n[INFOSEPARATOR]\nEC: 27170\n",
               "timings": [
               ],
               "children": [
                {
                  "name": "HASH_JOIN",
                  "timing":0.000001,
                  "cardinality":0,
                  "extra_info": "INNER\nmovie_id = id\n\n[INFOSEPARATOR]\nEC: 26929\n",
                  "timings": [
                  ],
                  "children": [
                   {
                     "name": "USE_BF",
                     "timing":0.000050,
                     "cardinality":0,
                     "extra_info": "",
                     "timings": [
                     ],
                     "children": [
                      {
                        "name": "PROJECTION",
                        "timing":0.000004,
                        "cardinality":3917,
                        "extra_info": "#1\n#2\n#3\n",
                        "timings": [
                        ],
                        "children": [
                         {
                           "name": "FILTER",
                           "timing":0.000192,
                           "cardinality":3917,
                           "extra_info": "IN (...)\n[INFOSEPARATOR]\nEC: 2967144",
                           "timings": [
                           ],
                           "children": [
                            {
                              "name": "HASH_JOIN",
                              "timing":0.001517,
                              "cardinality":102400,
                              "extra_info": "MARK\ninfo = #0\n\n[INFOSEPARATOR]\nEC: 2967144\n",
                              "timings": [
                              ],
                              "children": [
                               {
                                 "name": "SEQ_SCAN ",
                                 "timing":0.002460,
                                 "cardinality":102400,
                                 "extra_info": "movie_info\n[INFOSEPARATOR]\ninfo\nmovie_id\ninfo_type_id\n[INFOSEPARATOR]\nEC: 2967144",
                                 "timings": [
                                 ],
                                 "children": [
                                 ]
                               }
,
                               {
                                 "name": "COLUMN_DATA_SCAN",
                                 "timing":0.000005,
                                 "cardinality":8,
                                 "extra_info": "",
                                 "timings": [
                                 ],
                                 "children": [
                                 ]
                               }
                              ]
                            }
                           ]
                         }
                        ]
                      }
                     ]
                   }
,
                   {
                     "name": "HASH_JOIN",
                     "timing":0.000072,
                     "cardinality":0,
                     "extra_info": "INNER\ncompany_type_id = id\n\n[INFOSEPARATOR]\nEC: 24468\n",
                     "timings": [
                     ],
                     "children": [
                      {
                        "name": "HASH_JOIN",
                        "timing":0.064120,
                        "cardinality":0,
                        "extra_info": "INNER\nmovie_id = id\n\n[INFOSEPARATOR]\nEC: 97874\n",
                        "timings": [
                        ],
                        "children": [
                         {
                           "name": "CREATE_BF",
                           "timing":0.000013,
                           "cardinality":0,
                           "extra_info": "",
                           "timings": [
                           ],
                           "children": [
                            {
                              "name": "USE_BF",
                              "timing":0.000000,
                              "cardinality":0,
                              "extra_info": "",
                              "timings": [
                              ],
                              "children": [
                               {
                                 "name": "USE_BF",
                                 "timing":0.000357,
                                 "cardinality":0,
                                 "extra_info": "",
                                 "timings": [
                                 ],
                                 "children": [
                                  {
                                    "name": "FILTER",
                                    "timing":0.050928,
                                    "cardinality":24025,
                                    "extra_info": "(contains(note, '(theatrical)') AND contains(note, '(France)'))\n[INFOSEPARATOR]\nEC: 521825",
                                    "timings": [
                                    ],
                                    "children": [
                                     {
                                       "name": "SEQ_SCAN ",
                                       "timing":0.147882,
                                       "cardinality":2609129,
                                       "extra_info": "movie_companies\n[INFOSEPARATOR]\nnote\nmovie_id\ncompany_type_id\n[INFOSEPARATOR]\nEC: 521825",
                                       "timings": [
                                       ],
                                       "children": [
                                       ]
                                     }
                                    ]
                                  }
                                 ]
                               }
                              ]
                            }
                           ]
                         }
,
                         {
                           "name": "CREATE_BF",
                           "timing":0.092065,
                           "cardinality":1012920,
                           "extra_info": "",
                           "timings": [
                           ],
                           "children": [
                            {
                              "name": "SEQ_SCAN ",
                              "timing":0.283571,
                              "cardinality":1012920,
                              "extra_info": "title\n[INFOSEPARATOR]\nid\ntitle\n[INFOSEPARATOR]\nFilters: production_year>2005 AND production_year IS NOT NULL\n\n[INFOSEPARATOR]\nEC: 505662",
                              "timings": [
                              ],
                              "children": [
                              ]
                            }
                           ]
                         }
                        ]
                      }
,
                      {
                        "name": "CREATE_BF",
                        "timing":0.003152,
                        "cardinality":1,
                        "extra_info": "",
                        "timings": [
                        ],
                        "children": [
                         {
                           "name": "SEQ_SCAN ",
                           "timing":0.000874,
                           "cardinality":1,
                           "extra_info": "company_type\n[INFOSEPARATOR]\nid\n[INFOSEPARATOR]\nFilters: kind=production companies AND kind IS NOT NULL\n\n[INFOSEPARATOR]\nEC: 1",
                           "timings": [
                           ],
                           "children": [
                           ]
                         }
                        ]
                      }
                     ]
                   }
                  ]
                }
,
                {
                  "name": "SEQ_SCAN ",
                  "timing":0.001460,
                  "cardinality":113,
                  "extra_info": "info_type\n[INFOSEPARATOR]\nid\n[INFOSEPARATOR]\nEC: 113",
                  "timings": [
                  ],
                  "children": [
                  ]
                }
               ]
             }
            ]
          }
         ]
       }
      ]
    }
   ]
}